zero_3rdparty/__init__.py
zero_3rdparty/cache_ttl.py
zero_3rdparty/closable_queue.py
zero_3rdparty/dataclass_utils.py
zero_3rdparty/datetime_utils.py
zero_3rdparty/decorator_globals.py
zero_3rdparty/dependency.py
zero_3rdparty/dict_nested.py
zero_3rdparty/dict_utils.py
zero_3rdparty/enum_utils.py
zero_3rdparty/env_reader.py
zero_3rdparty/env_temp.py
zero_3rdparty/error.py
zero_3rdparty/file_utils.py
zero_3rdparty/future.py
zero_3rdparty/humps.py
zero_3rdparty/id_creator.py
zero_3rdparty/iter_utils.py
zero_3rdparty/logging_utils.py
zero_3rdparty/object_name.py
zero_3rdparty/py.typed
zero_3rdparty/run_env.py
zero_3rdparty/sections.py
zero_3rdparty/str_utils.py
zero_3rdparty/timeparse.py
zero_3rdparty/type_dict.py
zero_3rdparty/_internal/__init__.py
zero_3rdparty/_internal/sections.py
zero_3rdparty-0.102.0.dist-info/METADATA
zero_3rdparty-0.102.0.dist-info/WHEEL
zero_3rdparty-0.102.0.dist-info/licenses/LICENSE
zero_3rdparty-0.102.0.dist-info/RECORD
