Metadata-Version: 2.4
Name: zero-3rdparty
Version: 0.102.0
Author-email: EspenAlbert <espen.albert1@gmail.com>
License-Expression: MIT
License-File: LICENSE
Classifier: Development Status :: 4 - Beta
Classifier: Programming Language :: Python :: 3.13
Classifier: Programming Language :: Python :: 3.14
Requires-Python: >=3.13
